Metadata-Version: 1.0
Name: Gaussian-Bolinomial-distributions
Version: 0.1
Summary: Gaussian and bolinomial distributions
Home-page: UNKNOWN
Author: UNKNOWN
Author-email: UNKNOWN
License: UNKNOWN
Platform: UNKNOWN
